dynamic_sitemap/__init__.py
dynamic_sitemap/config.py
dynamic_sitemap/core.py
dynamic_sitemap/exceptions.py
dynamic_sitemap/helpers.py
dynamic_sitemap/items.py
dynamic_sitemap/renderers.py
dynamic_sitemap/validators.py
dynamic_sitemap/contrib/__init__.py
dynamic_sitemap/contrib/flask.py
dynamic_sitemap-1.0.0a1.dist-info/LICENSE.txt
dynamic_sitemap-1.0.0a1.dist-info/METADATA
dynamic_sitemap-1.0.0a1.dist-info/WHEEL
dynamic_sitemap-1.0.0a1.dist-info/top_level.txt
dynamic_sitemap-1.0.0a1.dist-info/RECORD
