Metadata-Version: 2.1
Name: dynamic-sitemap
Version: 1.0.0a1
Summary: The sitemap generator for Python projects.
Home-page: https://github.com/KazakovDenis/dynamic-sitemap
Author: Denis Kazakov
Author-email: denis@kazakov.ru.net
License: MIT
Keywords: sitemap
Platform: UNKNOWN
Classifier: Development Status :: 3 - Alpha
Classifier: Framework :: Flask
Classifier: Intended Audience :: Developers
Classifier: License :: OSI Approved :: MIT License
Classifier: Operating System :: OS Independent
Classifier: Programming Language :: Python :: 3
Classifier: Programming Language :: Python :: 3.6
Classifier: Programming Language :: Python :: 3.7
Classifier: Programming Language :: Python :: 3.8
Classifier: Topic :: Internet
Requires-Python: >=3.6
License-File: LICENSE.txt
Requires-Dist: pytz (>=2020.1)
